xklearn/__init__.py
xklearn/models/__init__.py
xklearn/models/fold_estimator.py
xklearn/models/fold_lgbm.py
xklearn/models/stacking_classifier.py
xklearn/models/stacking_regressor.py
xklearn/preprocessing/__init__.py
xklearn/preprocessing/count_encoder.py
xklearn/preprocessing/target_encoder.py
xklearn-0.0.1.dist-info/LICENSE
xklearn-0.0.1.dist-info/METADATA
xklearn-0.0.1.dist-info/WHEEL
xklearn-0.0.1.dist-info/top_level.txt
xklearn-0.0.1.dist-info/RECORD
