Metadata-Version: 2.1
Name: xklearn
Version: 0.0.1
Summary: Handy machine learning tools in the spirit of scikit-learn.
Home-page: https://github.com/simon-larsson/extrakit-learn
Author: Simon Larsson
Author-email: simonlarsson0@gmail.com
License: MIT
Platform: UNKNOWN
Classifier: License :: OSI Approved :: MIT License
Classifier: Programming Language :: Python :: 3 :: Only
Classifier: Topic :: Scientific/Engineering
Requires-Dist: numpy
Requires-Dist: sklearn
